api_processor/__init__.py
api_processor/exception/__init__.py
api_processor/exception/rest_ws_exception.py
api_processor/facade/__init__.py
api_processor/facade/rest_ws_facade.py
api_processor/helper/__init__.py
api_processor/helper/retry/__init__.py
api_processor/helper/retry/retry_executor.py
api_processor/helper/retry/retry_executor_ex.py
api_processor/interface/__init__.py
api_processor/interface/rest_ws_delegate.py
api_processor/interface/rest_ws_handler.py
api_processor/model/__init__.py
api_processor/model/rest_ws_request.py
api_processor/model/rest_ws_response.py
api_processor/test/__init__.py
api_processor/test/ping_pong_test.py
api_processor/test/delegate/__init__.py
api_processor/test/delegate/ping_pong_ws_delegate.py
api_processor/test/handler/__init__.py
api_processor/test/handler/ping_pong_ws_handler.py
api_processor/test/model/__init__.py
api_processor/test/model/ping_pong_request.py
api_processor/test/model/ping_pong_response.py
api_processor-0.0.1.dist-info/LICENSE
api_processor-0.0.1.dist-info/METADATA
api_processor-0.0.1.dist-info/WHEEL
api_processor-0.0.1.dist-info/top_level.txt
api_processor-0.0.1.dist-info/RECORD
